{ 
    "ua": "",
    "homeUrl": "https://www.4kcz.com/",
    "cateNode": "//div[contains(@class,'xiaoyinqing')]/a",
    "cateName": "/text()",
    "cateId": "/@href",
    "cateIdR": "/vodtype/(\\d+)/",
    "cateManual": {},
    "homeVodNode": "//div[contains(@class, 'vodlist')]//a[contains(@class, 'aplus-exp')]",
    "homeVodName": "/@title",
    "homeVodId": "/@href",
    "homeVodIdR": "/voddetail/(\\w+)/",
    "homeVodImg": "/div/@data-original",
    "homeVodImgR": "\\S+(http\\S+)",
    "homeVodMark": "/span[contains(@class,'pack-prb hidden')]/text()",
    "cateUrl": "https://www.4kcz.com/vodshow/{cateId}/page/{catePg}.html",
    "cateVodNode": "//div[contains(@class, 'vodlist')]//a[contains(@class, 'aplus-exp')]",
    "cateVodName": "/@title",
    "cateVodId": "/@href",
    "cateVodIdR": "/voddetail/(\\w+)/",
    "cateVodImg": "/div/@data-original",
    "cateVodImgR": "\\S+(http\\S+)",
    "cateVodMark": "/span[contains(@class,'pack-prb hidden')]/text()",
    "dtUrl": "https://www.4kcz.com/voddetail/{vid}/",
    "dtNode": "//body",
    "dtName": "//div[@class='play-detail']/h1/span/@title",
    "dtNameR": "",
    "dtImg": "//div[@class='s-cover box']/a/img/@src",
    "dtImgR": "",
    "dtCate": "//span[contains(text(),'类型')]/following-sibling::a/text()",
    "dtArea": "//span[contains(text(),'地区')]/following-sibling::a/text()",
    "dtYear": "//span[contains(text(),'年代')]/following-sibling::a/text()",
    "dtDirector": "//span[contains(text(),'导演')]/following-sibling::a/text()",
    "dtActor": "//span[contains(text(),'演员')]/following-sibling::a/text()",
    "dtDesc": "//div[@class='desc_txt cf ec-palytcji cor3']/span/text()",
    "dtMark": "",
    "dtFromNode": "//a[contains(@class,'swiper-slide')]",
    "dtFromName": "/text()",
    "dtFromNameR": "",
    "dtUrlNode": "//ul[@class='content_playlist cf']",
    "dtUrlSubNode": "/li/a",
    "dtUrlId": "@href",
    "dtUrlIdR": "/vodplay/(\\S+)/",
    "dtUrlName": "/text()",
    "dtUrlNameR": "",
    "playUrl": "https://www.4kcz.com/vodplay/{playUrl}/",
    "playUa": "",
    "searchUrl": "https://www.4kcz.com/index.php/ajax/suggest?mid=1&wd={wd}&limit=20",
    "scVodNode": "json:list",
    "scVodName": "name",
    "scVodId": "id",
    "scVodIdR": "",
    "scVodImg": "pic",
    "scVodMark": ""
}